r2api/__init__.py
r2api/converter/__init__.py
r2api/converter/allacciate_il_grembiule.py
r2api/converter/base_converter.py
r2api/converter/fatto_in_casa.py
r2api/converter/giallo_zafferano.py
r2api/converter/molliche_di_zucchero.py
r2api/converter/ricette_di_max.py
r2api/translate/__init__.py
r2api/translate/apply_translation.py
r2api/utilities/__init__.py
r2api/utilities/errors.py
r2api/utilities/unit_conversion.py
r2api-0.2.1.dist-info/LICENSE
r2api-0.2.1.dist-info/METADATA
r2api-0.2.1.dist-info/WHEEL
r2api-0.2.1.dist-info/top_level.txt
r2api-0.2.1.dist-info/RECORD
