Metadata-Version: 2.1
Name: r2api
Version: 0.2.1
Summary: A small package to translate an Italian recipe and its units into English and imperial units using Google Translate
Home-page: https://github.com/benyakirten/r2api
Author: Benyakir Horowitz
Author-email: benyakir.horowitz@gmail.com
License: UNKNOWN
Platform: UNKNOWN
Classifier: Programming Language :: Python :: 3
Classifier: License :: OSI Approved :: MIT License
Classifier: Operating System :: OS Independent
Classifier: Development Status :: 3 - Alpha
Requires-Python: >=3.6
License-File: LICENSE
Requires-Dist: beautifulsoup4 (>=4.9.3)
Requires-Dist: bs4 (>=0.0.1)
Requires-Dist: requests (>=2.4.0)
